discord_simple/__init__.py
discord_simple/bot.py
discord_simple/transport.py
discord_simple/models/__init__.py
discord_simple/models/message.py
discord_simple/models/user.py
discord_simple-0.0.1.17.dist-info/DESCRIPTION.rst
discord_simple-0.0.1.17.dist-info/METADATA
discord_simple-0.0.1.17.dist-info/RECORD
discord_simple-0.0.1.17.dist-info/WHEEL
discord_simple-0.0.1.17.dist-info/metadata.json
discord_simple-0.0.1.17.dist-info/top_level.txt
