Metadata-Version: 2.0
Name: discord-simple
Version: 0.0.1.17
Summary: Discord simple API
Home-page: https://github.com/askovpen/discord_simple/
Author: Alexander N. Skovpen
Author-email: a.n.skovpen@gmail.com
License: LGPLv3
Platform: UNKNOWN
Classifier: Development Status :: 3 - Alpha
Classifier: Intended Audience :: Developers
Classifier: Programming Language :: Python :: 2.7
Classifier: Programming Language :: Python :: 3.4
Requires-Dist: certifi
Requires-Dist: urllib3 (>=1.10)
Requires-Dist: websocket-client (==0.37.0)
Provides-Extra: json
Requires-Dist: ujson; extra == 'json'
